{"nodes": [{"id": "c_users_utente_desktop_coffeeware_coffeeware_new_coffeeware_src_components_landing_sitefooter_tsx", "label": "SiteFooter.tsx", "file_type": "code", "source_file": "C:\\Users\\utente\\Desktop\\coffeeware\\coffeeware-new\\coffeeware\\src\\components\\landing\\SiteFooter.tsx", "source_location": "L1"}, {"id": "landing_sitefooter_nav", "label": "NAV", "file_type": "code", "source_file": "C:\\Users\\utente\\Desktop\\coffeeware\\coffeeware-new\\coffeeware\\src\\components\\landing\\SiteFooter.tsx", "source_location": "L5"}, {"id": "landing_sitefooter_contacts", "label": "CONTACTS", "file_type": "code", "source_file": "C:\\Users\\utente\\Desktop\\coffeeware\\coffeeware-new\\coffeeware\\src\\components\\landing\\SiteFooter.tsx", "source_location": "L12"}, {"id": "landing_sitefooter_sitefooter", "label": "SiteFooter()", "file_type": "code", "source_file": "C:\\Users\\utente\\Desktop\\coffeeware\\coffeeware-new\\coffeeware\\src\\components\\landing\\SiteFooter.tsx", "source_location": "L18"}], "edges": [{"source": "c_users_utente_desktop_coffeeware_coffeeware_new_coffeeware_src_components_landing_sitefooter_tsx", "target": "react_router_dom", "relation": "imports_from", "context": "import", "confidence": "EXTRACTED", "source_file": "C:\\Users\\utente\\Desktop\\coffeeware\\coffeeware-new\\coffeeware\\src\\components\\landing\\SiteFooter.tsx", "source_location": "L1", "weight": 1.0}, {"source": "c_users_utente_desktop_coffeeware_coffeeware_new_coffeeware_src_components_landing_sitefooter_tsx", "target": "lucide_react", "relation": "imports_from", "context": "import", "confidence": "EXTRACTED", "source_file": "C:\\Users\\utente\\Desktop\\coffeeware\\coffeeware-new\\coffeeware\\src\\components\\landing\\SiteFooter.tsx", "source_location": "L2", "weight": 1.0}, {"source": "c_users_utente_desktop_coffeeware_coffeeware_new_coffeeware_src_components_landing_sitefooter_tsx", "target": "c_users_utente_desktop_coffeeware_coffeeware_new_coffeeware_src_components_landing_wordmark_tsx", "relation": "imports_from", "context": "import", "confidence": "EXTRACTED", "source_file": "C:\\Users\\utente\\Desktop\\coffeeware\\coffeeware-new\\coffeeware\\src\\components\\landing\\SiteFooter.tsx", "source_location": "L3", "weight": 1.0}, {"source": "c_users_utente_desktop_coffeeware_coffeeware_new_coffeeware_src_components_landing_sitefooter_tsx", "target": "landing_sitefooter_nav", "relation": "contains", "confidence": "EXTRACTED", "source_file": "C:\\Users\\utente\\Desktop\\coffeeware\\coffeeware-new\\coffeeware\\src\\components\\landing\\SiteFooter.tsx", "source_location": "L5", "weight": 1.0}, {"source": "c_users_utente_desktop_coffeeware_coffeeware_new_coffeeware_src_components_landing_sitefooter_tsx", "target": "landing_sitefooter_contacts", "relation": "contains", "confidence": "EXTRACTED", "source_file": "C:\\Users\\utente\\Desktop\\coffeeware\\coffeeware-new\\coffeeware\\src\\components\\landing\\SiteFooter.tsx", "source_location": "L12", "weight": 1.0}, {"source": "c_users_utente_desktop_coffeeware_coffeeware_new_coffeeware_src_components_landing_sitefooter_tsx", "target": "landing_sitefooter_sitefooter", "relation": "contains", "confidence": "EXTRACTED", "source_file": "C:\\Users\\utente\\Desktop\\coffeeware\\coffeeware-new\\coffeeware\\src\\components\\landing\\SiteFooter.tsx", "source_location": "L18", "weight": 1.0}], "raw_calls": [{"caller_nid": "landing_sitefooter_sitefooter", "callee": "map", "is_member_call": true, "source_file": "C:\\Users\\utente\\Desktop\\coffeeware\\coffeeware-new\\coffeeware\\src\\components\\landing\\SiteFooter.tsx", "source_location": "L35"}, {"caller_nid": "landing_sitefooter_sitefooter", "callee": "map", "is_member_call": true, "source_file": "C:\\Users\\utente\\Desktop\\coffeeware\\coffeeware-new\\coffeeware\\src\\components\\landing\\SiteFooter.tsx", "source_location": "L60"}, {"caller_nid": "landing_sitefooter_sitefooter", "callee": "getFullYear", "is_member_call": true, "source_file": "C:\\Users\\utente\\Desktop\\coffeeware\\coffeeware-new\\coffeeware\\src\\components\\landing\\SiteFooter.tsx", "source_location": "L74"}]}