{"nodes": [{"id": "c_users_utente_desktop_coffeeware_coffeeware_new_coffeeware_src_components_home_header_tsx", "label": "Header.tsx", "file_type": "code", "source_file": "C:\\Users\\utente\\Desktop\\coffeeware\\coffeeware-new\\coffeeware\\src\\components\\home\\Header.tsx", "source_location": "L1"}, {"id": "home_header_header", "label": "Header()", "file_type": "code", "source_file": "C:\\Users\\utente\\Desktop\\coffeeware\\coffeeware-new\\coffeeware\\src\\components\\home\\Header.tsx", "source_location": "L3"}], "edges": [{"source": "c_users_utente_desktop_coffeeware_coffeeware_new_coffeeware_src_components_home_header_tsx", "target": "computer_png", "relation": "imports_from", "context": "import", "confidence": "EXTRACTED", "source_file": "C:\\Users\\utente\\Desktop\\coffeeware\\coffeeware-new\\coffeeware\\src\\components\\home\\Header.tsx", "source_location": "L1", "weight": 1.0}, {"source": "c_users_utente_desktop_coffeeware_coffeeware_new_coffeeware_src_components_home_header_tsx", "target": "home_header_header", "relation": "contains", "confidence": "EXTRACTED", "source_file": "C:\\Users\\utente\\Desktop\\coffeeware\\coffeeware-new\\coffeeware\\src\\components\\home\\Header.tsx", "source_location": "L3", "weight": 1.0}], "raw_calls": []}